eth2deposit/__init__.py
eth2deposit/credentials.py
eth2deposit/deposit.py
eth2deposit/settings.py
eth2deposit/__pycache__/__init__.cpython-37.pyc
eth2deposit/key_handling/__init__.py
eth2deposit/key_handling/keystore.py
eth2deposit/key_handling/key_derivation/__init__.py
eth2deposit/key_handling/key_derivation/mnemonic.py
eth2deposit/key_handling/key_derivation/path.py
eth2deposit/key_handling/key_derivation/tree.py
eth2deposit/utils/__init__.py
eth2deposit/utils/ascii_art.py
eth2deposit/utils/constants.py
eth2deposit/utils/crypto.py
eth2deposit/utils/ssz.py
eth2deposit/utils/validation.py
tests/test_key_handling/__init__.py
tests/test_key_handling/test_keystore.py
tests/test_key_handling/test_key_derivation/__init__.py
tests/test_key_handling/test_key_derivation/test_mnemonic.py
tests/test_key_handling/test_key_derivation/test_path.py
tests/test_key_handling/test_key_derivation/test_tree.py
eth2deposit-0.2.2.dist-info/LICENSE
eth2deposit-0.2.2.dist-info/METADATA
eth2deposit-0.2.2.dist-info/WHEEL
eth2deposit-0.2.2.dist-info/top_level.txt
eth2deposit-0.2.2.dist-info/RECORD
